{
  "categories": [
    {
      "id": 1,
      "name": "资次速"
    },
    {
      "id": 2,
      "name": "志色查院"
    },
    {
      "id": 3,
      "name": "县五它山"
    },
    {
      "id": 4,
      "name": "即飞会"
    }
  ],
  "products": [
    {
      "id": 1,
      "name": "料斗六我",
      "categoryId": 2,
      "dec": "导全务一须其这省已就示响最。",
      "price": 908.68
    },
    {
      "id": 2,
      "name": "严音便温",
      "categoryId": 2,
      "dec": "府从分因圆开高取节保先与水类。",
      "price": 687.53
    },
    {
      "id": 3,
      "name": "五和求容",
      "categoryId": 2,
      "dec": "际力边交原类思热空价存得。",
      "price": 219.64
    },
    {
      "id": 4,
      "name": "但全己",
      "categoryId": 1,
      "dec": "因门本金就标属往样可西写走种。",
      "price": 418.52
    },
    {
      "id": 5,
      "name": "但先规子",
      "categoryId": 2,
      "dec": "为资进近队想思实精是已毛油织。",
      "price": 742.83
    },
    {
      "id": 6,
      "name": "员约照每",
      "categoryId": 1,
      "dec": "清农万响律酸容手类气格基思。",
      "price": 624.85
    },
    {
      "id": 7,
      "name": "红目基身",
      "categoryId": 3,
      "dec": "以则五还战水研有况学按格。",
      "price": 70.92
    },
    {
      "id": 8,
      "name": "资上对进",
      "categoryId": 2,
      "dec": "他中放书却族所存提该铁斯思干。",
      "price": 515.24
    },
    {
      "id": 9,
      "name": "程状上米消",
      "categoryId": 4,
      "dec": "入约少更目标油平积国种高回。",
      "price": 499.12
    },
    {
      "id": 10,
      "name": "员使目",
      "categoryId": 3,
      "dec": "即并历养又将战集元须证派过到机内。",
      "price": 660.87
    },
    {
      "id": 11,
      "name": "类当矿团",
      "categoryId": 2,
      "dec": "去米你合么革它其节作多识条养。",
      "price": 569.82
    },
    {
      "id": 12,
      "name": "商米并写做",
      "categoryId": 3,
      "dec": "术些条用力学放自新情合力型本系理。",
      "price": 548.67
    },
    {
      "id": 13,
      "name": "率应元",
      "categoryId": 1,
      "dec": "干本原究干五照可多把究织区品。",
      "price": 192.38
    },
    {
      "id": 14,
      "name": "些定为事",
      "categoryId": 4,
      "dec": "日实况个这区会世点标效想最本厂。",
      "price": 142.04
    },
    {
      "id": 15,
      "name": "情南小",
      "categoryId": 1,
      "dec": "专置拉多口了物观指军值组却安。",
      "price": 826.45
    },
    {
      "id": 16,
      "name": "山备证中者",
      "categoryId": 2,
      "dec": "度强干工动想的求该其切采带自选快近。",
      "price": 302.36
    },
    {
      "id": 17,
      "name": "也是位的高",
      "categoryId": 3,
      "dec": "素别不收集事团广主商办总电般此标。",
      "price": 342.17
    },
    {
      "id": 18,
      "name": "确手有识县",
      "categoryId": 4,
      "dec": "南器思些少真革强清社真间速回红照约。",
      "price": 833.71
    },
    {
      "id": 19,
      "name": "阶每决提",
      "categoryId": 1,
      "dec": "思志石引化程物空厂区斯回此再两命。",
      "price": 261.65
    },
    {
      "id": 20,
      "name": "又始压事该",
      "categoryId": 2,
      "dec": "转阶光率论声流断至华内边方变酸。",
      "price": 202.62
    },
    {
      "id": 21,
      "name": "保即制六大",
      "categoryId": 3,
      "dec": "边京边记适土省五众最律政县。",
      "price": 830.83
    },
    {
      "id": 22,
      "name": "住正日利却",
      "categoryId": 4,
      "dec": "己周能农断万被林被张写列较。",
      "price": 182.27
    },
    {
      "id": 23,
      "name": "着相众",
      "categoryId": 3,
      "dec": "带叫车世活明收往准结理写千员。",
      "price": 155.61
    },
    {
      "id": 24,
      "name": "论作受们",
      "categoryId": 3,
      "dec": "再今说没标名计题领大不正在。",
      "price": 805.37
    },
    {
      "id": 25,
      "name": "间收处",
      "categoryId": 1,
      "dec": "高矿造学术带生育料管而在等持引务人特。",
      "price": 807.72
    },
    {
      "id": 26,
      "name": "圆较除",
      "categoryId": 3,
      "dec": "整设影往到件王向老步器展地列选设。",
      "price": 585.91
    },
    {
      "id": 27,
      "name": "酸众最",
      "categoryId": 2,
      "dec": "社应三设市何外西观什何白。",
      "price": 809.36
    },
    {
      "id": 28,
      "name": "半这工",
      "categoryId": 2,
      "dec": "代收命算时机向不满人约党品达受基。",
      "price": 941.57
    },
    {
      "id": 29,
      "name": "回气从表",
      "categoryId": 3,
      "dec": "角部元即人边花石斗业业效标三。",
      "price": 70.57
    },
    {
      "id": 30,
      "name": "民得院积",
      "categoryId": 3,
      "dec": "土除断红军的快龙多林置次空由是。",
      "price": 994.23
    },
    {
      "id": 31,
      "name": "算集得",
      "categoryId": 4,
      "dec": "更更程它海压可种属图铁与三已价合争。",
      "price": 128.08
    },
    {
      "id": 32,
      "name": "身省务",
      "categoryId": 2,
      "dec": "联真条把计然马气质格京工高但象。",
      "price": 275.43
    },
    {
      "id": 33,
      "name": "体包后",
      "categoryId": 1,
      "dec": "过量再农号机农三确群众体我党相。",
      "price": 17.75
    },
    {
      "id": 34,
      "name": "组备白",
      "categoryId": 4,
      "dec": "究种厂还毛场备记年全活空候。",
      "price": 439.83
    },
    {
      "id": 35,
      "name": "几作整话列",
      "categoryId": 3,
      "dec": "变斗来八深地亲写极月处又只海按。",
      "price": 628.67
    },
    {
      "id": 36,
      "name": "运林农证见",
      "categoryId": 4,
      "dec": "金基则分资它般千采相据石美示重。",
      "price": 535.11
    },
    {
      "id": 37,
      "name": "想专系除民",
      "categoryId": 2,
      "dec": "好交战内把真低写两使数已低。",
      "price": 252.61
    },
    {
      "id": 38,
      "name": "须写按车",
      "categoryId": 3,
      "dec": "合日形及院回表先象电把也斯听南级出斗。",
      "price": 2.14
    },
    {
      "id": 39,
      "name": "保群她信",
      "categoryId": 4,
      "dec": "理问改元入众史来信界计育接标。",
      "price": 330.69
    },
    {
      "id": 40,
      "name": "到建新战",
      "categoryId": 3,
      "dec": "收们例原容主强传听位价林四。",
      "price": 334.69
    },
    {
      "id": 41,
      "name": "过识省工",
      "categoryId": 3,
      "dec": "了便带走解位那五图构层他素起验公新调。",
      "price": 846.38
    },
    {
      "id": 42,
      "name": "之快代",
      "categoryId": 1,
      "dec": "则五高联听支会者门千况处。",
      "price": 19.62
    },
    {
      "id": 43,
      "name": "组结转",
      "categoryId": 2,
      "dec": "律量快国风龙周因也照路也习比低起。",
      "price": 320.86
    },
    {
      "id": 44,
      "name": "立队质",
      "categoryId": 3,
      "dec": "内表员示金如省江高领都门员改求手。",
      "price": 211.35
    },
    {
      "id": 45,
      "name": "器马百该",
      "categoryId": 2,
      "dec": "条头极之制合同明调权八深构划山东问使。",
      "price": 421.25
    },
    {
      "id": 46,
      "name": "想证本形",
      "categoryId": 3,
      "dec": "运目并基去矿门部原式易社使比正业基。",
      "price": 737.12
    },
    {
      "id": 47,
      "name": "高也支加",
      "categoryId": 3,
      "dec": "称整民理任学值命者决对日年教。",
      "price": 364.23
    },
    {
      "id": 48,
      "name": "称两物单",
      "categoryId": 2,
      "dec": "器活为里号具必集率而件近证准色变新。",
      "price": 285.07
    },
    {
      "id": 49,
      "name": "状头事真",
      "categoryId": 4,
      "dec": "能用果观教参又约解如三物入记。",
      "price": 706.26
    },
    {
      "id": 50,
      "name": "层得毛油",
      "categoryId": 4,
      "dec": "书因过及离相术接接少么除方解。",
      "price": 92.41
    },
    {
      "id": 51,
      "name": "写还集列",
      "categoryId": 2,
      "dec": "想值务线江六世在如安说由展。",
      "price": 753.39
    },
    {
      "id": 52,
      "name": "广院响向",
      "categoryId": 3,
      "dec": "设并确日极信族于细直报太各候识各。",
      "price": 340.54
    },
    {
      "id": 53,
      "name": "酸他接",
      "categoryId": 4,
      "dec": "斗中规完文运步统为般区器平。",
      "price": 21.41
    },
    {
      "id": 54,
      "name": "员率计安",
      "categoryId": 3,
      "dec": "战般毛品历别五其包起候前领京这年府。",
      "price": 436.37
    },
    {
      "id": 55,
      "name": "大政原听",
      "categoryId": 1,
      "dec": "别矿料以几现条低同料太单千积其酸而片。",
      "price": 907.68
    },
    {
      "id": 56,
      "name": "象次来",
      "categoryId": 3,
      "dec": "队备进起展统适便红向时图决部一级是。",
      "price": 743.12
    },
    {
      "id": 57,
      "name": "下据风构",
      "categoryId": 2,
      "dec": "可产志专照按光收感并毛立相红调。",
      "price": 774.42
    },
    {
      "id": 58,
      "name": "张层变需是",
      "categoryId": 2,
      "dec": "性么设精保领每代身学那子么构包交。",
      "price": 306.43
    },
    {
      "id": 59,
      "name": "史力边形那",
      "categoryId": 3,
      "dec": "物而音要机革资具适它此照再利又代。",
      "price": 112.52
    }
  ],
  "carts": [
    {
      "name": "程状上米消",
      "productId": 9,
      "price": 499.12,
      "num": 1,
      "id": 2
    },
    {
      "name": "些定为事",
      "productId": 14,
      "price": 142.04,
      "num": 1,
      "id": 3
    },
    {
      "name": "确手有识县",
      "productId": 18,
      "price": 833.71,
      "num": 1,
      "id": 4
    },
    {
      "name": "住正日利却",
      "productId": 22,
      "price": 182.27,
      "num": 1,
      "id": 5
    }
  ]
}